pymondo/__init__.py
pymondo/data.py
pymondo/downloader.py
pymondo/mondo.py
pymondo-0.0.15.dist-info/LICENSE
pymondo-0.0.15.dist-info/METADATA
pymondo-0.0.15.dist-info/WHEEL
pymondo-0.0.15.dist-info/top_level.txt
pymondo-0.0.15.dist-info/RECORD
