Metadata-Version: 2.1
Name: pymondo
Version: 0.0.15
Summary: python wrapper for mondo
Home-page: https://github.com/roy29fuku/pymondo
Author: Ryota Yamada
Author-email: roy29fuku@gmail.com
License: UNKNOWN
Platform: UNKNOWN
Classifier: Programming Language :: Python :: 3
Classifier: Programming Language :: Python :: 3.8
Classifier: License :: OSI Approved :: MIT License
Classifier: Operating System :: MacOS
Requires-Python: >=3.8
Requires-Dist: appnope (==0.1.0)
Requires-Dist: attrs (==19.3.0)
Requires-Dist: backcall (==0.1.0)
Requires-Dist: bleach (==3.1.1)
Requires-Dist: certifi (==2019.11.28)
Requires-Dist: chain-norm (==0.0.12)
Requires-Dist: chardet (==3.0.4)
Requires-Dist: decorator (==4.4.1)
Requires-Dist: defusedxml (==0.6.0)
Requires-Dist: docutils (==0.16)
Requires-Dist: entrypoints (==0.3)
Requires-Dist: idna (==2.9)
Requires-Dist: ipykernel (==5.1.4)
Requires-Dist: ipython (==7.12.0)
Requires-Dist: ipython-genutils (==0.2.0)
Requires-Dist: ipywidgets (==7.5.1)
Requires-Dist: jaconv (==0.2.4)
Requires-Dist: jedi (==0.16.0)
Requires-Dist: Jinja2 (==2.11.1)
Requires-Dist: jsonschema (==3.2.0)
Requires-Dist: jupyter (==1.0.0)
Requires-Dist: jupyter-client (==6.0.0)
Requires-Dist: jupyter-console (==6.1.0)
Requires-Dist: jupyter-core (==4.6.3)
Requires-Dist: keyring (==21.1.0)
Requires-Dist: MarkupSafe (==1.1.1)
Requires-Dist: mistune (==0.8.4)
Requires-Dist: nbconvert (==5.6.1)
Requires-Dist: nbformat (==5.0.4)
Requires-Dist: notebook (==6.0.3)
Requires-Dist: pandocfilters (==1.4.2)
Requires-Dist: parso (==0.6.1)
Requires-Dist: pexpect (==4.8.0)
Requires-Dist: pickleshare (==0.7.5)
Requires-Dist: pipdeptree (==0.13.2)
Requires-Dist: pkginfo (==1.5.0.1)
Requires-Dist: prometheus-client (==0.7.1)
Requires-Dist: prompt-toolkit (==3.0.3)
Requires-Dist: ptyprocess (==0.6.0)
Requires-Dist: Pygments (==2.5.2)
Requires-Dist: pyrsistent (==0.15.7)
Requires-Dist: python-dateutil (==2.8.1)
Requires-Dist: pyzmq (==18.1.1)
Requires-Dist: qtconsole (==4.6.0)
Requires-Dist: readme-renderer (==24.0)
Requires-Dist: requests (==2.23.0)
Requires-Dist: requests-toolbelt (==0.9.1)
Requires-Dist: Send2Trash (==1.5.0)
Requires-Dist: six (==1.14.0)
Requires-Dist: terminado (==0.8.3)
Requires-Dist: testpath (==0.4.4)
Requires-Dist: tornado (==6.0.3)
Requires-Dist: tqdm (==4.43.0)
Requires-Dist: traitlets (==4.3.3)
Requires-Dist: twine (==3.1.1)
Requires-Dist: urllib3 (==1.25.8)
Requires-Dist: wcwidth (==0.1.8)
Requires-Dist: webencodings (==0.5.1)
Requires-Dist: widgetsnbextension (==3.5.1)
Requires-Dist: word2number (==1.1)
